{
     // Place your snippets for dart here. Each snippet is defined under a snippet name and has a prefix, body and 
     // description. The prefix is what is used to trigger the snippet and the body will be expanded and inserted. Possible variables are:
     // $1, $2 for tab stops, $0 for the final cursor position, and ${1:label}, ${2:another} for placeholders. Placeholders with the 
     // same ids are connected.
     // Example:
     // "Print to console": {
     // 	"prefix": "log",
     // 	"body": [
     // 		"console.log('$1');",
     // 		"$2"
     // 	],
     // 	"description": "Log output to console"
     // }
     "material package": {
          "prefix": "PFMD",
          "body": [
               "import 'package:flutter/material.dart';"
          ],
          "description": "material package"
     },
     //----------------------------------------------------------------------------------
     "longline": {
          "prefix": "lll",
          "body": [
               "//---------------------------------------------------------------------------------"
          ],
          "description": "longline"
     },
     //----------------------------------------------------------------------------------
     "Mediumline": {
          "prefix": "ll",
          "body": [
               "//--------------------------------------------------------------"
          ],
          "description": "longline"
     },
     //----------------------------------------------------------------------------------
     "shortline": {
          "prefix": "l",
          "body": [
               "//----------------------------------------------"
          ],
          "description": "longline"
     },
     //----------------------------------------------------------------------------------
     "Flutter Main Template": {
          "prefix": "MAIN-TEMPLATE",
          "body": [
               "import 'package:flutter/material.dart';",
               "",
               "void main() {",
               "  runApp(const MyApp());",
               "}",
               "",
               "class MyApp extends StatelessWidget {",
               "  const MyApp({",
               "    Key? key,",
               "  }) : super(key: key);",
               "  @override",
               "  Widget build(BuildContext context) {",
               "    return const MaterialApp(",
               "      debugShowCheckedModeBanner: false,",
               "      title: \"My Application Title\",",
               "      home: Material(",
               "        child: MyChildClass(),",
               "      ),",
               "    );",
               "  }",
               "}",
               "",
               "class MyChildClass extends StatefulWidget {",
               "  const MyChildClass({",
               "    Key? key,",
               "  }) : super(key: key);",
               "  @override",
               "  _MyChildClassState createState() => _MyChildClassState();",
               "}",
               "",
               "class _MyChildClassState extends State<MyChildClass> {",
               "  @override",
               "  Widget build(BuildContext context) {",
               "    return Scaffold(",
               "      drawer: drawerManagement(),",
               "      appBar: AppBar(",
               "        title: const Text(\"Flutter Main Class\"),",
               "        leadingWidth: 60,",
               "",
               "        leading: Builder(",
               "          builder: (context) => IconButton(",
               "            iconSize: 36,",
               "            splashRadius: 30,",
               "            hoverColor: Colors.white24,",
               "            splashColor: Colors.white,",
               "            icon: const Icon(Icons.menu_rounded),",
               "            onPressed: () => Scaffold.of(context).openDrawer(),",
               "          ),",
               "        ),",
               "",
               "        actions: [",
               "          Container(",
               "            padding: const EdgeInsets.symmetric(horizontal: 30),",
               "            child: IconButton(",
               "              onPressed: () {},",
               "              iconSize: 36,",
               "              hoverColor: Colors.white24,",
               "              splashRadius: 24,",
               "              splashColor: Colors.white12,",
               "              icon: const Icon(Icons.search_sharp),",
               "            ),",
               "          ),",
               "        ],",
               "        elevation: 20.0,",
               "        shadowColor: Colors.white,",
               "        backgroundColor: Colors.indigo,",
               "        brightness: Brightness.light,",
               "        // centerTitle: true,",
               "        foregroundColor: Colors.amber,",
               "        toolbarHeight: 72,",
               "        titleSpacing: 20,",
               "        titleTextStyle: const TextStyle(",
               "          color: Colors.white,",
               "          fontWeight: FontWeight.bold,",
               "        ),",
               "      ),",
               "      body: Center(",
               "        child: Text(",
               "          \"Flutter Main Class\",",
               "          style: TextStyle(",
               "            fontSize: 40,",
               "            fontWeight: FontWeight.bold,",
               "            color: Colors.indigo.shade900,",
               "          ),",
               "        ),",
               "      ),",
               "    );",
               "  }",
               "",
               "  //--------------------------------------------------------------",
               "",
               "  drawerManagement() {",
               "    return Drawer(",
               "      child: ListView(",
               "        children: [",
               "          UserAccountsDrawerHeader(",
               "            decoration: BoxDecoration(",
               "              color: Colors.indigo.shade700,",
               "            ),",
               "            accountName: const Text(\"Your Name\"),",
               "            accountEmail: const Text(\"youremail@gmail.com\"),",
               "            currentAccountPicture: CircleAvatar(",
               "              backgroundColor: Colors.white,",
               "              foregroundColor: Colors.indigo.shade900,",
               "              child: Text(",
               "                \"NAME\",",
               "                style: TextStyle(",
               "                  color: Colors.indigo.shade900,",
               "                  fontWeight: FontWeight.bold,",
               "                ),",
               "              ),",
               "            ),",
               "          ),",
               "          ListTile(",
               "            title: const Text(",
               "              \"Home\",",
               "              style: TextStyle(",
               "                  fontSize: 16, fontWeight: FontWeight.bold, letterSpacing: 1),",
               "            ),",
               "            leading: Icon(",
               "              Icons.home,",
               "              color: Colors.indigo.shade900,",
               "            ),",
               "            autofocus: true,",
               "            hoverColor: Colors.grey.shade300,",
               "            focusColor: Colors.white10,",
               "            dense: true,",
               "            onLongPress: () {},",
               "            onTap: () {},",
               "            // tileColor: Colors.blue,",
               "          ),",
               "          Divider(",
               "            color: Colors.blue.shade900,",
               "            thickness: 1.0,",
               "            endIndent: 3,",
               "            indent: 3,",
               "          ),",
               "          ListTile(",
               "            title: const Text(",
               "              \"Gallary\",",
               "              style: TextStyle(",
               "                  fontSize: 16, fontWeight: FontWeight.bold, letterSpacing: 1),",
               "            ),",
               "            leading: Icon(",
               "              Icons.image,",
               "              color: Colors.indigo.shade900,",
               "            ),",
               "            autofocus: true,",
               "            hoverColor: Colors.grey.shade300,",
               "            focusColor: Colors.white10,",
               "            dense: true,",
               "            onLongPress: () {},",
               "            onTap: () {},",
               "            // tileColor: Colors.blue,",
               "          ),",
               "          Divider(",
               "            color: Colors.blue.shade900,",
               "            thickness: 1.0,",
               "            endIndent: 3,",
               "            indent: 3,",
               "          ),",
               "          ListTile(",
               "            title: const Text(",
               "              \"Document\",",
               "              style: TextStyle(",
               "                  fontSize: 16, fontWeight: FontWeight.bold, letterSpacing: 1),",
               "            ),",
               "            leading: Icon(",
               "              Icons.document_scanner,",
               "              color: Colors.indigo.shade900,",
               "            ),",
               "            autofocus: true,",
               "            hoverColor: Colors.grey.shade300,",
               "            focusColor: Colors.white10,",
               "            dense: true,",
               "            onLongPress: () {},",
               "            onTap: () {},",
               "            // tileColor: Colors.blue,",
               "          ),",
               "          Divider(",
               "            color: Colors.blue.shade900,",
               "            thickness: 1.0,",
               "            endIndent: 3,",
               "            indent: 3,",
               "          ),",
               "          ListTile(",
               "            title: const Text(",
               "              \"Account\",",
               "              style: TextStyle(",
               "                  fontSize: 16, fontWeight: FontWeight.bold, letterSpacing: 1),",
               "            ),",
               "            leading: Icon(",
               "              Icons.account_balance,",
               "              color: Colors.indigo.shade900,",
               "            ),",
               "            autofocus: true,",
               "            hoverColor: Colors.grey.shade300,",
               "            focusColor: Colors.white10,",
               "            dense: true,",
               "            onLongPress: () {},",
               "            onTap: () {},",
               "            // tileColor: Colors.blue,",
               "          ),",
               "          Divider(",
               "            color: Colors.blue.shade900,",
               "            thickness: 1.0,",
               "            endIndent: 3,",
               "            indent: 3,",
               "          ),",
               "          ListTile(",
               "            title: const Text(",
               "              \"About Us\",",
               "              style: TextStyle(",
               "                  fontSize: 16, fontWeight: FontWeight.bold, letterSpacing: 1),",
               "            ),",
               "            leading: Icon(",
               "              Icons.people,",
               "              color: Colors.indigo.shade900,",
               "            ),",
               "            autofocus: true,",
               "            hoverColor: Colors.grey.shade300,",
               "            focusColor: Colors.white10,",
               "            dense: true,",
               "            onLongPress: () {},",
               "            onTap: () {},",
               "            // tileColor: Colors.blue,",
               "          ),",
               "          Divider(",
               "            color: Colors.blue.shade900,",
               "            thickness: 1.0,",
               "            endIndent: 3,",
               "            indent: 3,",
               "          ),",
               "        ],",
               "      ),",
               "    );",
               "  }",
               "  //--------------------------------------------------------------",
               "",
               "}",
               ""
          ],
          "description": "Flutter Main Template"
     },
     //----------------------------------------------------------------------------------
     "BottomNavigationbar": {
          "prefix": "BOTTOMNAVIGATIONBAR",
          "body": [
               "//--------------------------------------------------------------",
               "   bnbManagement() {",
               "    return BottomNavigationBar(",
               "      items: <BottomNavigationBarItem>[",
               "        BottomNavigationBarItem(",
               "          icon: Icon(",
               "            Icons.home_outlined,",
               "            color: Colors.white,",
               "          ),",
               "          label: \"Home\",",
               "          backgroundColor: Colors.indigo.shade800,",
               "          tooltip: \"Home\",",
               "        ),",
               "        BottomNavigationBarItem(",
               "          icon: Icon(",
               "            Icons.article_rounded,",
               "            color: Colors.white,",
               "          ),",
               "          label: \"View Note\",",
               "          backgroundColor: Colors.indigo.shade800,",
               "          tooltip: \"View Note\",",
               "        ),",
               "        BottomNavigationBarItem(",
               "          icon: Icon(",
               "            Icons.edit_outlined,",
               "            color: Colors.white,",
               "          ),",
               "          label: \"Edit Note\",",
               "          backgroundColor: Colors.indigo.shade800,",
               "          tooltip: \"Edit Note\",",
               "        ),",
               "        BottomNavigationBarItem(",
               "          icon: Icon(",
               "            Icons.delete_outline,",
               "            color: Colors.white,",
               "          ),",
               "          label: \"Delete Note\",",
               "          backgroundColor: Colors.indigo.shade800,",
               "          tooltip: \"Delete Note\",",
               "        ),",
               "      ],",
               "      type: BottomNavigationBarType.fixed,",
               "      selectedItemColor: Colors.white,",
               "     // currentIndex: _curruntIndex,",
               "      elevation: 20.0,",
               "      showUnselectedLabels: true,",
               "      // unselectedFontSize: ,",
               "      selectedLabelStyle: TextStyle(),",
               "      unselectedItemColor: Colors.white24,",
               "      iconSize: 30.0,",
               "      showSelectedLabels: true,",
               "      selectedFontSize: 14.0,",
               "     // onTap: _changePageFunction,",
               "      backgroundColor: Colors.indigo.shade900,",
               "    );",
               "  }",
               "",
               "  //--------------------------------------------------------------",
               "  void _changePageFunction(int index) {",
               "    setState(() {",
               "      _curruntIndex = index;",
               "    });",
               "  }",
               "}"
          ],
          "description": "BottomNavigationbar"
     },
     //----------------------------------------------------------------------------------
     "Flutter Appbar": {
          "prefix": "APPBAR-FUNCTION",
          "body": [
               " //--------------------------------------------------------------",
               "  appbarManagement() {",
               "    return AppBar(",
               "      title: const Text(\"Flutter Class Page\"),",
               "      leadingWidth: 60,",
               "",
               "      leading: Builder(",
               "        builder: (context) => IconButton(",
               "          iconSize: 36,",
               "          splashRadius: 30,",
               "          hoverColor: Colors.white24,",
               "          splashColor: Colors.white,",
               "          icon: const Icon(Icons.menu_rounded),",
               "          onPressed: () => Scaffold.of(context).openDrawer(),",
               "        ),",
               "      ),",
               "",
               "      actions: [",
               "        Container(",
               "          padding: const EdgeInsets.symmetric(horizontal: 30),",
               "          child: IconButton(",
               "            onPressed: () {},",
               "            iconSize: 36,",
               "            hoverColor: Colors.white24,",
               "            splashRadius: 24,",
               "            splashColor: Colors.white12,",
               "            icon: const Icon(Icons.search_sharp),",
               "          ),",
               "        ),",
               "      ],",
               "      elevation: 20.0,",
               "      shadowColor: Colors.white,",
               "      backgroundColor: Colors.indigo,",
               "      brightness: Brightness.light,",
               "      // centerTitle: true,",
               "      foregroundColor: Colors.amber,",
               "      toolbarHeight: 72,",
               "      titleSpacing: 20,",
               "      titleTextStyle: const TextStyle(",
               "        color: Colors.white,",
               "        fontWeight: FontWeight.bold,",
               "      ),",
               "    );",
               "  }",
               "  //--------------------------------------------------------------"
          ],
          "description": "Flutter Appbar"
     },
     //----------------------------------------------------------------------------------
     "Flutter Drawer": {
          "prefix": "DRAWER-FUNCTION",
          "body": [
               " //--------------------------------------------------------------",
               "",
               "  drawerManagement() {",
               "    return Drawer(",
               "      child: ListView(",
               "        children: [",
               "          UserAccountsDrawerHeader(",
               "            decoration: BoxDecoration(",
               "              color: Colors.indigo.shade700,",
               "            ),",
               "            accountName: const Text(\"Your Name\"),",
               "            accountEmail: const Text(\"youremail@gmail.com\"),",
               "            currentAccountPicture: CircleAvatar(",
               "              backgroundColor: Colors.white,",
               "              foregroundColor: Colors.indigo.shade900,",
               "              child: Text(",
               "                \"NAME\",",
               "                style: TextStyle(",
               "                  color: Colors.indigo.shade900,",
               "                  fontWeight: FontWeight.bold,",
               "                ),",
               "              ),",
               "            ),",
               "          ),",
               "          ListTile(",
               "            title: const Text(",
               "              \"Home\",",
               "              style: TextStyle(",
               "                  fontSize: 16, fontWeight: FontWeight.bold, letterSpacing: 1),",
               "            ),",
               "            leading: Icon(",
               "              Icons.home,",
               "              color: Colors.indigo.shade900,",
               "            ),",
               "            autofocus: true,",
               "            hoverColor: Colors.grey.shade300,",
               "            focusColor: Colors.white10,",
               "            dense: true,",
               "            onLongPress: () {},",
               "            onTap: () {},",
               "            // tileColor: Colors.blue,",
               "          ),",
               "          Divider(",
               "            color: Colors.blue.shade900,",
               "            thickness: 1.0,",
               "            endIndent: 3,",
               "            indent: 3,",
               "          ),",
               "          ListTile(",
               "            title: const Text(",
               "              \"Gallary\",",
               "              style: TextStyle(",
               "                  fontSize: 16, fontWeight: FontWeight.bold, letterSpacing: 1),",
               "            ),",
               "            leading: Icon(",
               "              Icons.image,",
               "              color: Colors.indigo.shade900,",
               "            ),",
               "            autofocus: true,",
               "            hoverColor: Colors.grey.shade300,",
               "            focusColor: Colors.white10,",
               "            dense: true,",
               "            onLongPress: () {},",
               "            onTap: () {},",
               "            // tileColor: Colors.blue,",
               "          ),",
               "          Divider(",
               "            color: Colors.blue.shade900,",
               "            thickness: 1.0,",
               "            endIndent: 3,",
               "            indent: 3,",
               "          ),",
               "          ListTile(",
               "            title: const Text(",
               "              \"Document\",",
               "              style: TextStyle(",
               "                  fontSize: 16, fontWeight: FontWeight.bold, letterSpacing: 1),",
               "            ),",
               "            leading: Icon(",
               "              Icons.document_scanner,",
               "              color: Colors.indigo.shade900,",
               "            ),",
               "            autofocus: true,",
               "            hoverColor: Colors.grey.shade300,",
               "            focusColor: Colors.white10,",
               "            dense: true,",
               "            onLongPress: () {},",
               "            onTap: () {},",
               "            // tileColor: Colors.blue,",
               "          ),",
               "          Divider(",
               "            color: Colors.blue.shade900,",
               "            thickness: 1.0,",
               "            endIndent: 3,",
               "            indent: 3,",
               "          ),",
               "          ListTile(",
               "            title: const Text(",
               "              \"Account\",",
               "              style: TextStyle(",
               "                  fontSize: 16, fontWeight: FontWeight.bold, letterSpacing: 1),",
               "            ),",
               "            leading: Icon(",
               "              Icons.account_balance,",
               "              color: Colors.indigo.shade900,",
               "            ),",
               "            autofocus: true,",
               "            hoverColor: Colors.grey.shade300,",
               "            focusColor: Colors.white10,",
               "            dense: true,",
               "            onLongPress: () {},",
               "            onTap: () {},",
               "            // tileColor: Colors.blue,",
               "          ),",
               "          Divider(",
               "            color: Colors.blue.shade900,",
               "            thickness: 1.0,",
               "            endIndent: 3,",
               "            indent: 3,",
               "          ),",
               "          ListTile(",
               "            title: const Text(",
               "              \"About Us\",",
               "              style: TextStyle(",
               "                  fontSize: 16, fontWeight: FontWeight.bold, letterSpacing: 1),",
               "            ),",
               "            leading: Icon(",
               "              Icons.people,",
               "              color: Colors.indigo.shade900,",
               "            ),",
               "            autofocus: true,",
               "            hoverColor: Colors.grey.shade300,",
               "            focusColor: Colors.white10,",
               "            dense: true,",
               "            onLongPress: () {},",
               "            onTap: () {},",
               "            // tileColor: Colors.blue,",
               "          ),",
               "          Divider(",
               "            color: Colors.blue.shade900,",
               "            thickness: 1.0,",
               "            endIndent: 3,",
               "            indent: 3,",
               "          ),",
               "        ],",
               "      ),",
               "    );",
               "  }",
               "  //--------------------------------------------------------------"
          ],
          "description": "Flutter Drawer"
     },
     //----------------------------------------------------------------------------------
     "ScaffoldWidget": {
          "prefix": "SCAFFOLD",
          "body": [
               "Scaffold(",
               "      appBar: AppBar(",
               "        title:const Text(\"Class Page\"),",
               "        leading:const Icon(Icons.menu),",
               "        actions: [",
               "          IconButton(onPressed: () {}, icon:const Icon(Icons.notifications)),",
               "          IconButton(onPressed: () {}, icon:const Icon(Icons.search_sharp)),",
               "        ],",
               "        elevation: 20.0,",
               "        shadowColor: Colors.white,",
               "        backgroundColor: Colors.indigo,",
               "        brightness: Brightness.light,",
               "        // centerTitle: true,",
               "        foregroundColor: Colors.amber,",
               "        toolbarHeight: 50,",
               "        titleSpacing: 20,",
               "        titleTextStyle:const TextStyle(",
               "          color: Colors.white,",
               "          fontWeight: FontWeight.bold,",
               "        ),",
               "      ),",
               "      body: Center(",
               "        child: Text(",
               "          \"Class Page\",",
               "          style: TextStyle(",
               "            fontWeight: FontWeight.bold,",
               "            color: Colors.indigo.shade900,",
               "          ),",
               "        ),",
               "      ),",
               "    );"
          ],
          "description": "ScaffoldWidget"
     },
     //----------------------------------------------------------------------------------
     "FirebaseMainFuncton": {
          "prefix": "FIREBASE MAIN",
          "body": [
               "void main() async {",
               "  WidgetsFlutterBinding.ensureInitialized();",
               "  await Firebase.initializeApp();",
               "  runApp(MyApp());",
               "}"
          ],
          "description": "FirebaseMainFuncton"
     },
     //----------------------------------------------------------------------------------
     "MainFuncton": {
          "prefix": "MAIN FUNCTION",
          "body": [
               "void main(){",
               "  runApp(MyApp());",
               "}"
          ],
          "description": "MainFuncton"
     },
     //----------------------------------------------------------------------------------
     "Responsive Users Interface": {
          "prefix": "RESPONSIVE",
          "body": [
               "import 'package:flutter/material.dart';",
               "",
               "class Responsive extends StatelessWidget {",
               "  final Widget largeScreen;",
               "  final Widget? mediumScreen;",
               "  final Widget? smallScreen;",
               "",
               "  const Responsive(",
               "      {Key? key,",
               "      required this.largeScreen,",
               "      this.mediumScreen,",
               "      this.smallScreen})",
               "      : super(key: key);",
               "",
               "  static bool isLargeScreen(BuildContext context) {",
               "    return MediaQuery.of(context).size.width > 1200;",
               "  }",
               "",
               "  static bool isMediumScreen(BuildContext context) {",
               "    return MediaQuery.of(context).size.width >= 800 &&",
               "        MediaQuery.of(context).size.width <= 1200;",
               "  }",
               "",
               "  static bool isSmallScreen(BuildContext context) {",
               "    return MediaQuery.of(context).size.width < 800;",
               "  }",
               "",
               "  @override",
               "  Widget build(BuildContext context) {",
               "    return LayoutBuilder(builder: (context, constraints) {",
               "      if (constraints.maxWidth > 1200) {",
               "        return largeScreen;",
               "      } else if (constraints.maxWidth <= 1200 && constraints.maxWidth >= 800) {",
               "        return mediumScreen ?? largeScreen;",
               "      } else {",
               "        return smallScreen ?? largeScreen;",
               "      }",
               "    });",
               "  }",
               "}",
               ""
          ],
          "description": "Responsive Users Interface"
     },
     //----------------------------------------------------------------------------------
     "Media Query Screen Size": {
          "prefix": "SCREENSIZE",
          "body": [
               "var screenSize = MediaQuery.of(context).size;"
          ],
          "description": "Media Query Screen Size"
     },
     //----------------------------------------------------------------------------------
     "ScreenLayout": {
          "prefix": "SCREEN-LAYOUT",
          "body": [
               "Container(",
               "      child: LayoutBuilder(",
               "        builder: (context, constraint) {",
               "          if (constraint.maxWidth >= 992) {",
               "            return Container();",
               "          } else if (constraint.maxWidth >= 768 && constraint.maxWidth < 992) {",
               "            return Container();",
               "          } else if (constraint.maxWidth > 600 && constraint.maxWidth < 768) {",
               "            return Container();",
               "          } else if (constraint.maxWidth <= 600) {",
               "            return Container();",
               "          } else {",
               "            return Container();",
               "          }",
               "        },",
               "      ),",
               "    );"
          ],
          "description": "ScreenLayout"
     },
     //----------------------------------------------------------------------------------
     "Margin All": {
          "prefix": "M-ALL",
          "body": [
               "margin:const EdgeInsets.all(5),"
          ],
          "description": "Margin All"
     },
     //----------------------------------------------------------------------------------
     "Margin Symmetric": {
          "prefix": "M-SYMT",
          "body": [
               "margin:const EdgeInsets.symmetric(horizontal: 5,vertical: 5),"
          ],
          "description": "Margin Symmetric"
     },
     //----------------------------------------------------------------------------------
     "Margin Left Top Right Bottom": {
          "prefix": "M-LTRB",
          "body": [
               "margin:const EdgeInsets.fromLTRB(5, 5, 5, 5),"
          ],
          "description": "Margin Left Top Right Bottom"
     },
     //----------------------------------------------------------------------------------
     "Margin Only": {
          "prefix": "M-ONLY",
          "body": [
               "margin:const EdgeInsets.only(top: 5, left: 5, right: 5, bottom: 5),"
          ],
          "description": "Margin Only"
     },
     //----------------------------------------------------------------------------------
     "Padding All": {
          "prefix": "P-ALL",
          "body": [
               "padding:const EdgeInsets.all(5),"
          ],
          "description": "Margin All"
     },
     //----------------------------------------------------------------------------------
     "Padding Symmetric": {
          "prefix": "P-SYMT",
          "body": [
               "padding:const EdgeInsets.symmetric(horizontal: 5,vertical: 5),"
          ],
          "description": "Margin Symmetric"
     },
     //----------------------------------------------------------------------------------
     "Padding Left Top Right Bottom": {
          "prefix": "P-LTRB",
          "body": [
               "padding:const EdgeInsets.fromLTRB(5, 5, 5, 5),"
          ],
          "description": "Margin Left Top Right Bottom"
     },
     //----------------------------------------------------------------------------------
     "Padding Only": {
          "prefix": "P-ONLY",
          "body": [
               "padding:const EdgeInsets.only(top: 5, left: 5, right: 5, bottom: 5),"
          ],
          "description": "Margin Only"
     },
     //----------------------------------------------------------------------------------
     "ListViewBuilder": {
          "prefix": "FUTURE-LISTVIEW-BUILDER",
          "body": [
               "//--------------------------------------------------------------",
               "  FutureBuilder<List<UsersInformation>> buildFutureBuilder(Size screenSize) {",
               "    return FutureBuilder(",
               "      future: usersServices.fetchUsersDetailsbyModel(),",
               "      builder: (context, snapshot) {",
               "        if (snapshot.hasData) {",
               "          List<UsersInformation> details =",
               "              snapshot.data as List<UsersInformation>;",
               "          return ListView.builder(",
               "              shrinkWrap: true,",
               "              itemCount: details.length,",
               "              itemBuilder: (BuildContext context, int index) {",
               "                return Container(",
               "                  child: ListTile(",
               "                    onTap: () {},",
               "                    leading: CircleAvatar(",
               "                      child: Text(\"P\"),",
               "                    ),",
               "                    title: Text(details[index].email),",
               "                  ),",
               "                );",
               "              });",
               "        } else if (snapshot.hasError) {",
               "          return Center(",
               "            child: Text(",
               "              \"${snapshot.error}\",",
               "            ),",
               "          );",
               "        } else {",
               "          return Center(",
               "            child: CircularProgressIndicator(),",
               "          );",
               "        }",
               "        // By default show a loading spinner.",
               "      },",
               "    );",
               "  }",
               "  //---------------------------------------------------------------------------------"
          ],
          "description": "ListViewBuilder"
     },
     //----------------------------------------------------------------------------------
     "Elevated Button": {
          "prefix": "ELEVATED-BUTTON",
          "body": [
               "ElevatedButton(",
               "child: Container(",
               "padding: EdgeInsets.symmetric(",
               "vertical: 10, horizontal: 40),",
               "child: Text(\"Button\"),",
               "),",
               "onPressed: (){},",
               "style: ElevatedButton.styleFrom(",
               "primary: Colors.red,",
               "onPrimary: Colors.white,",
               "shape: RoundedRectangleBorder(",
               "borderRadius: BorderRadius.circular(32.0),",
               "),",
               "),",
               "),",
               "                           "
          ],
          "description": "Array display function"
     },
     //----------------------------------------------------------------------------------
     "Flutter Class Key": {
          "prefix": "CLASS-KEY",
          "body": [
               " const HomepageClass({Key? key}) : super(key: key);"
          ],
          "description": "Flutter Class Key"
     },
     //----------------------------------------------------------------------------------
     "Flutter New Class": {
          "prefix": "NEW-CLASS",
          "body": [
               "import 'package:flutter/material.dart';",
               "",
               "class MyNewClassName extends StatefulWidget {",
               "  const MyNewClassName({",
               "    Key? key,",
               "  }) : super(key: key);",
               "  @override",
               "  _MyNewClassNameState createState() => _MyNewClassNameState();",
               "}",
               "",
               "class _MyNewClassNameState extends State<MyNewClassName> {",
               "  @override",
               "  Widget build(BuildContext context) {",
               "    return Scaffold(",
               "      appBar: buildAppBar(),",
               "      body: SingleChildScrollView(",
               "        child: SafeArea(",
               "          child: Column(",
               "            children: [",
               "              SizedBox(height: 300),",
               "              Center(",
               "                child: Text(",
               "                  \"My New Class\",",
               "                  style: TextStyle(",
               "                    fontSize: 20,",
               "                    fontWeight: FontWeight.bold,",
               "                    color: Colors.indigo.shade900,",
               "                  ),",
               "                ),",
               "              ),",
               "            ],",
               "          ),",
               "        ),",
               "      ),",
               "    );",
               "  }",
               "",
               "//---------------------------------------------------------------------------------",
               "  AppBar buildAppBar() {",
               "    return AppBar(",
               "      title: const Text(\"New Class\"),",
               "      backgroundColor: Colors.lightBlue.shade900,",
               "      brightness: Brightness.dark,",
               "      elevation: 0,",
               "      centerTitle: true,",
               "      shadowColor: Colors.transparent,",
               "      toolbarHeight: 72,",
               "      leading: IconButton(",
               "        onPressed: () {},",
               "        icon: Icon(",
               "          Icons.arrow_back_outlined,",
               "          color: Colors.white,",
               "        ),",
               "      ),",
               "      actions: [",
               "        IconButton(",
               "          onPressed: () {},",
               "          icon: Icon(",
               "            Icons.menu,",
               "            color: Colors.white,",
               "          ),",
               "        ),",
               "      ],",
               "    );",
               "  }",
               "}",
               ""
          ],
          "description": "Flutter New Class"
     },
     //----------------------------------------------------------------------------------
     "Flutter Long List": {
          "prefix": "LONG-LIST-EXAMPLE",
          "body": [
               "class LongListExample extends StatefulWidget {",
               "  const LongListExample({Key? key}) : super(key: key);",
               "  @override",
               "  State<LongListExample> createState() => _LongListExampleState();",
               "}",
               "",
               "class _LongListExampleState extends State<LongListExample> {",
               "  List items = List<String>.generate(50, (i) => 'Item $i');",
               "  @override",
               "  Widget build(BuildContext context) {",
               "    String title = 'Long List';",
               "",
               "    return MaterialApp(",
               "      title: title,",
               "      home: Scaffold(",
               "        appBar: AppBar(",
               "          title: Text(title),",
               "        ),",
               "        body: ListView.builder(",
               "          itemCount: items.length,",
               "          itemBuilder: (context, index) {",
               "            return ListTile(",
               "              title: Text('${items[index]}'),",
               "            );",
               "          },",
               "        ),",
               "      ),",
               "    );",
               "  }",
               "}",
               ""
          ],
          "description": "Flutter Long List"
     },
     //----------------------------------------------------------------------------------
     "GridView Builder": {
          "prefix": "GRID-VIEW-BUILDER",
          "body": [
               "import 'package:flutter/material.dart';",
               "import 'package:flutter_account/Application/Views/ScreenController/screen_responsive.dart';",
               "",
               "class GridViewExample extends StatefulWidget {",
               "  const GridViewExample({Key? key}) : super(key: key);",
               "  @override",
               "  State<GridViewExample> createState() => _GridViewExampleState();",
               "}",
               "",
               "class _GridViewExampleState extends State<GridViewExample> {",
               "  List personas = List<String>.generate(50, (i) => 'Item $i');",
               "  String fullname = \"New\";",
               "",
               "  @override",
               "  void initState() {",
               "    super.initState();",
               "  }",
               "",
               "  @override",
               "  Widget build(BuildContext context) {",
               "    return Scaffold(",
               "      appBar: AppBar(title: const Text(\"Title\")),",
               "      body: SingleChildScrollView(",
               "        child: Container(",
               "          padding: const EdgeInsets.all(5),",
               "          child: Builder(builder: (BuildContext context) {",
               "            if (Responsive.isLargeScreen(context)) {",
               "              return Container(",
               "                padding: const EdgeInsets.all(5),",
               "                child: buildGridView(4),",
               "              );",
               "            } else if (Responsive.isMediumScreen(context)) {",
               "              return Container(",
               "                padding: const EdgeInsets.all(5),",
               "                child: buildGridView(3),",
               "              );",
               "            } else {",
               "              return Container(",
               "                padding: const EdgeInsets.all(5),",
               "                child: buildGridView(1),",
               "              );",
               "            }",
               "          }),",
               "        ),",
               "      ),",
               "    );",
               "  }",
               "",
               "//--------------------------------------------------------------",
               "  GridView buildGridView(int screenpart) {",
               "    return GridView.builder(",
               "        shrinkWrap: true,",
               "        gridDelegate: SliverGridDelegateWithFixedCrossAxisCount(",
               "          crossAxisCount: screenpart,",
               "          childAspectRatio: (3 / 2),",
               "        ),",
               "        itemCount: personas.length,",
               "        itemBuilder: (BuildContext context, int index) {",
               "          return SingleChildScrollView(",
               "            child: Container(",
               "              padding: const EdgeInsets.all(5),",
               "              height: 300,",
               "              child: Card(",
               "                child: Center(",
               "                  child: Text(personas[index]),",
               "                ),",
               "              ),",
               "            ),",
               "          );",
               "        });",
               "  }",
               "}",
               ""
          ],
          "description": "GridView Builder"
     },
     //----------------------------------------------------------------------------------
     "Flutter Container": {
          "prefix": "CONTAINER",
          "body": [
               "Container(",
               "              height: 50,",
               "              width: MediaQuery.of(context).size.width,",
               "              color: Colors.indigo.shade900,",
               "              child: Center(",
               "                child: Text(",
               "                  \"Container Box\",",
               "                  style: TextStyle(",
               "                    color: Colors.white,",
               "                  ),",
               "                ),",
               "              ),",
               "            ),"
          ],
          "description": "Flutter Container"
     },
     //----------------------------------------------------------------------------------
     "Navigation": {
          "prefix": "NAVIGATION",
          "body": [
               " Navigator.push(context,",
               "  MaterialPageRoute(builder: (context) {",
               "  return ClassName();",
               "  }));"
          ],
          "description": "Navigation"
     },
     //----------------------------------------------------------------------------------
     "FlutterTextStyle": {
          "prefix": "TEXTSTYLE",
          "body": [
               " style: TextStyle(",
               "   fontSize: 18,",
               "    color: Colors.black,",
               "     fontWeight: FontWeight.normal,",
               "),"
          ],
          "description": "FlutterTextStyle"
     },
     //----------------------------------------------------------------------------------
     "Flutter new class": {
          "prefix": "FLUTTER CLASS",
          "body": [
               "import 'package:flutter/material.dart';",
               "",
               "class $0 extends StatefulWidget {",
               "  const $0({",
               "    Key? key,",
               "  }) : super(key: key);",
               "  @override",
               "  _$0State createState() => _$0State();",
               "}",
               "",
               "class _$0State extends State<$0> {",
               "  @override",
               "  Widget build(BuildContext context) {",
               "    return Container();",
               "  }",
               "}",
               ""
          ],
          "description": "Flutter new class"
     },
     //----------------------------------------------------------------------------------
     "Facebook Navigation": {
          "prefix": "PAGE NAVIGATION",
          "body": [
               " Navigator.push(context, MaterialPageRoute<void>(",
               "   builder: (BuildContext context) {",
               "   return const $0;",
               "     },",
               " ));"
          ],
          "description": "Facebook Navigation"
     }
     //----------------------------------------------------------------------------------
     //----------------------------------------------------------------------------------
     //----------------------------------------------------------------------------------
     //----------------------------------------------------------------------------------
     //----------------------------------------------------------------------------------
     //----------------------------------------------------------------------------------
     //----------------------------------------------------------------------------------
     //----------------------------------------------------------------------------------
}